[
  {
    "id": "e4626472-5bb9-490e-86c9-3c4f4782e72e",
    "effect": "forbid",
    "resource": "tool",
    "match": "shell_execute",
    "reason": "Prevents agents from executing arbitrary shell commands",
    "tags": ["security", "demo"]
  },
  {
    "id": "6e780ba2-88a9-41a2-90ca-e2e48a80dd11",
    "effect": "forbid",
    "resource": "tool",
    "match": "exec",
    "reason": "Prevents agents from executing arbitrary shell commands",
    "tags": ["security", "demo"]
  },
  {
    "id": "ec4e06c8-144c-485a-a263-6eb283c47587",
    "effect": "forbid",
    "resource": "tool",
    "match": "web_fetch",
    "reason": "Agent is not allowed to fetch external URLs",
    "tags": ["security", "demo"]
  }
]
